AlexnetImagenetClassificationWithDeepConvolutionalNeuralNetworksYiwen/README.md
AlexnetImagenetClassificationWithDeepConvolutionalNeuralNetworksYiwen/__init__.py
AlexnetImagenetClassificationWithDeepConvolutionalNeuralNetworksYiwen/__main__.py
AlexnetImagenetClassificationWithDeepConvolutionalNeuralNetworksYiwen/file.pdf
AlexnetImagenetClassificationWithDeepConvolutionalNeuralNetworksYiwen/index.html
alexnet_imagenet_classification_with_deep_convolutional_neural_networks_yiwen-2024.3.3.0.dist-info/METADATA
alexnet_imagenet_classification_with_deep_convolutional_neural_networks_yiwen-2024.3.3.0.dist-info/WHEEL
alexnet_imagenet_classification_with_deep_convolutional_neural_networks_yiwen-2024.3.3.0.dist-info/entry_points.txt
alexnet_imagenet_classification_with_deep_convolutional_neural_networks_yiwen-2024.3.3.0.dist-info/top_level.txt
alexnet_imagenet_classification_with_deep_convolutional_neural_networks_yiwen-2024.3.3.0.dist-info/RECORD
